kelvin_rest_api_client-2.3.0.dist-info/licenses/LICENSE
ucsschool/kelvin/client/__init__.py
ucsschool/kelvin/client/base.py
ucsschool/kelvin/client/exceptions.py
ucsschool/kelvin/client/py.typed
ucsschool/kelvin/client/role.py
ucsschool/kelvin/client/school.py
ucsschool/kelvin/client/school_class.py
ucsschool/kelvin/client/session.py
ucsschool/kelvin/client/user.py
ucsschool/kelvin/client/workgroup.py
kelvin_rest_api_client-2.3.0.dist-info/METADATA
kelvin_rest_api_client-2.3.0.dist-info/WHEEL
kelvin_rest_api_client-2.3.0.dist-info/top_level.txt
kelvin_rest_api_client-2.3.0.dist-info/RECORD
