Metadata-Version: 2.4
Name: kelvin-rest-api-client
Version: 2.3.0
Summary: Python library to interact with the UCS@school Kelvin REST API.
Home-page: https://github.com/univention/kelvin-rest-api-client
Author: Daniel Troeder
Author-email: troeder@univention.de
License: GNU Affero General Public License v3
Keywords: Univention UCS UCS@school REST
Classifier: Development Status :: 4 - Beta
Classifier: Intended Audience :: Developers
Classifier: License :: OSI Approved :: GNU Affero General Public License v3
Classifier: Natural Language :: English
Classifier: Operating System :: OS Independent
Classifier: Programming Language :: Python :: 3.7
Classifier: Programming Language :: Python :: 3.8
Classifier: Programming Language :: Python :: 3.9
Classifier: Programming Language :: Python :: 3.10
Classifier: Topic :: Software Development :: Libraries
Classifier: Topic :: System :: Systems Administration :: Authentication/Directory :: LDAP
Requires-Python: >=3.7
License-File: LICENSE
Requires-Dist: async-property<0.3.0,>=0.2.1
Requires-Dist: httpx>=0.23.1
Requires-Dist: lazy-object-proxy>=1.6.0
Requires-Dist: pyjwt<3.0.0,>=2.0.0
Requires-Dist: wheel>=0.36.2
Provides-Extra: development
Requires-Dist: docker>=5.0.0; extra == "development"
Requires-Dist: ldap3>=2.9; extra == "development"
Requires-Dist: ruamel.yaml>=0.17.4; extra == "development"
Requires-Dist: pre-commit>=2.12.1; extra == "development"
Requires-Dist: pytest-asyncio<=0.18.0,>=0.15.1; extra == "development"
Requires-Dist: pytest-mock>=3.7.0; extra == "development"
Requires-Dist: tox>=3.23.0; extra == "development"
Requires-Dist: pytest>=6.2.3; extra == "development"
Requires-Dist: Sphinx<6.0.0,>=5.0.0; extra == "development"
Requires-Dist: lazy-object-proxy>=1.6.0; extra == "development"
Requires-Dist: async-property<0.3.0,>=0.2.1; extra == "development"
Requires-Dist: httpx>=0.23.1; extra == "development"
Requires-Dist: coverage>=5.5; extra == "development"
Requires-Dist: pyjwt<3.0.0,>=2.0.0; extra == "development"
Requires-Dist: argh<1.0.0,>=0.26.0; extra == "development"
Requires-Dist: watchdog>=2.0.3; extra == "development"
Requires-Dist: wheel>=0.36.2; extra == "development"
Requires-Dist: twine>=3.4.1; extra == "development"
Requires-Dist: Faker<=15.0.0,>=8.1.1; extra == "development"
Requires-Dist: factory_boy<=4.0.0,>=3.0.0; extra == "development"
Dynamic: author
Dynamic: author-email
Dynamic: classifier
Dynamic: description
Dynamic: description-content-type
Dynamic: home-page
Dynamic: keywords
Dynamic: license
Dynamic: license-file
Dynamic: provides-extra
Dynamic: requires-dist
Dynamic: requires-python
Dynamic: summary
